WX_Push_Services/WX_Push_Services.py
WX_Push_Services/__init__.py
WX_Push_Services-1.0.24.data/scripts/WX_Push_Services.py
WX_Push_Services-1.0.24.dist-info/LICENSE
WX_Push_Services-1.0.24.dist-info/METADATA
WX_Push_Services-1.0.24.dist-info/WHEEL
WX_Push_Services-1.0.24.dist-info/entry_points.txt
WX_Push_Services-1.0.24.dist-info/top_level.txt
WX_Push_Services-1.0.24.dist-info/RECORD
